
{
  "id": "53531129-f111-46ff-8415-e10bdc599e76",
  "name": "my-project98",
  "values": [
    {
      "key": "host",
      "value": "https://api.europe-west1.gcp.commercetools.com",
      "enabled": true,
      "type": "text"
    },
    {
      "key": "auth_url",
      "value": "https://auth.europe-west1.gcp.commercetools.com",
      "enabled": true,
      "type": "text"
    },
    {
      "key": "projectKey",
      "value": "my-project98",
      "enabled": true,
      "type": "text"
    },
    {
      "key": "client_id",
      "value": "Zn03ugFjIoaOP5zfNAghuaMC",
      "enabled": true,
      "type": "text"
    },
    {
      "key": "client_secret",
      "value": "G-EXHhCAqosL5chavJKVOvv8INrsQa0T",
      "enabled": true,
      "type": "text"
    }
  ],
  "_postman_variable_scope": "environment",
  "_postman_exported_at": "2023-08-05T13:50:37.521Z",
  "_postman_exported_using": "Postman/6.0.10"
}
